CHANGES.rst
CONTRIBUTORS.rst
HOWTO_DEVELOP.rst
MANIFEST.in
README.rst
setup.cfg
setup.py
docs/LICENSE.GPL
docs/LICENSE.rst
docs/README
docs/readthedocs-requirements.txt
docs/_images/preview.png
docs/_images/settings-colophon_text--activated.png
docs/_images/settings-colophon_text--deactivated.png
docs/_images/settings-color_option--aqua.png
docs/_images/settings-color_option--blue.png
docs/_images/settings-color_option--brown.png
docs/_images/settings-color_option--default.png
docs/_images/settings-color_option--green.png
docs/_images/settings-color_option--orange.png
docs/_images/settings-color_option--purple.png
docs/_images/settings-color_option--red.png
docs/_images/settings-debug--activated.png
docs/_images/settings-email--activated.png
docs/_images/settings-email--deactivated.png
docs/_images/settings-footer_option--default.png
docs/_images/settings-footer_option--footer-default.png
docs/_images/settings-footer_text--activated.png
docs/_images/settings-footer_text--deactivated.png
docs/_images/settings-header_option--default.png
docs/_images/settings-header_option--header-default.png
docs/_images/settings-hide_colophon--activated.png
docs/_images/settings-hide_footer--activated.png
docs/_images/settings-hide_searchbox--activated.png
docs/_images/settings-layout_option--boxed.png
docs/_images/settings-layout_option--default.png
docs/_images/settings-layout_option--wide.png
docs/_images/settings-pattern_option--default.png
docs/_images/settings-pattern_option--none.png
docs/_images/settings-phone_number--activated.png
docs/_images/settings-phone_number--deactivated.png
docs/_images/settings-slogan--activated.png
docs/_images/settings-slogan--deactivated.png
docs/_images/setup_select_add_on.png
docs/_images/setup_select_add_on_installable.png
docs/_images/spirit_plone_theming_overview.png
docs/_images/theming_upload_btn.png
docs/_images/theming_upload_dialog.png
docs/source/conf.py
docs/source/customize.rst
docs/source/index.rst
docs/source/install.rst
src/plonetheme.barcelonetang.egg-info/PKG-INFO
src/plonetheme.barcelonetang.egg-info/SOURCES.txt
src/plonetheme.barcelonetang.egg-info/dependency_links.txt
src/plonetheme.barcelonetang.egg-info/entry_points.txt
src/plonetheme.barcelonetang.egg-info/namespace_packages.txt
src/plonetheme.barcelonetang.egg-info/not-zip-safe
src/plonetheme.barcelonetang.egg-info/requires.txt
src/plonetheme.barcelonetang.egg-info/top_level.txt
