Metadata-Version: 1.1
Name: plonetheme.barcelonetang
Version: 0.5
Summary: The Barceloneta NG Theme for Plone 5.
Home-page: https://github.com/it-spirit/plonetheme.barcelonetang
Author: it-spirit
Author-email: development@it-spir.it
License: GPL version 2
Download-URL: https://pypi.python.org/pypi/plonetheme.barcelonetang
Keywords: plone diazo
Platform: UNKNOWN
Classifier: Development Status :: 5 - Production/Stable
Classifier: Environment :: Web Environment
Classifier: Framework :: Plone
Classifier: Framework :: Plone :: 5.0
Classifier: Framework :: Plone :: 5.1
Classifier: Framework :: Plone :: Theme
Classifier: Intended Audience :: Developers
Classifier: License :: OSI Approved :: GNU General Public License v2 (GPLv2)
Classifier: Programming Language :: Python
Classifier: Programming Language :: Python :: 2.7
